[
  {
    "display": "\u4eca\u5929 03-26",
    "timestamp": 1616757550553
  },
  {
    "display": "\u5468\u516d 03-27",
    "timestamp": 1616843950553
  },
  {
    "display": "\u5468\u65e5 03-28",
    "timestamp": 1616930350553
  },
  {
    "display": "\u5468\u4e00 03-29",
    "timestamp": 1617016750553
  },
  {
    "display": "\u5468\u4e8c 03-30",
    "timestamp": 1617103150553
  },
  {
    "display": "\u5468\u4e09 03-31",
    "timestamp": 1617189550553
  },
  {
    "display": "\u5468\u56db 04-01",
    "timestamp": 1617275950553
  }
]